setup.py
funniest_mawe/__init__.py
funniest_mawe.egg-info/PKG-INFO
funniest_mawe.egg-info/SOURCES.txt
funniest_mawe.egg-info/dependency_links.txt
funniest_mawe.egg-info/not-zip-safe
funniest_mawe.egg-info/top_level.txt