Metadata-Version: 1.0
Name: funniest-mawe
Version: 0.1
Summary: Funny Python packaging test
Home-page: https://github.com/MaWeffm/funniest_mawe
Author: Martin Wegner
Author-email: ma.wegner@em.uni-frankfurt.de
License: MIT???
Platform: UNKNOWN
